sealevelDB/__init__.py
sealevelDB/sldb.py
sealevelDB/utilities.py
sealevelDB-0.0.1.dist-info/METADATA
sealevelDB-0.0.1.dist-info/WHEEL
sealevelDB-0.0.1.dist-info/top_level.txt
sealevelDB-0.0.1.dist-info/RECORD
